pygendocs/__init__.py
pygendocs/__main__.py
pygendocs-0.1.0.dist-info/LICENSE
pygendocs-0.1.0.dist-info/METADATA
pygendocs-0.1.0.dist-info/WHEEL
pygendocs-0.1.0.dist-info/RECORD
